kapteyn-2.3.dist-info/top_level.txt
kapteyn-2.3.dist-info/DESCRIPTION.rst
kapteyn-2.3.dist-info/RECORD
kapteyn-2.3.dist-info/metadata.json
kapteyn-2.3.dist-info/WHEEL
kapteyn-2.3.dist-info/METADATA
kapteyn/ascarray.cpython-33m.so
kapteyn/celestial.py
kapteyn/tabarray.py
kapteyn/wcsgrat.py
kapteyn/doccer.py
kapteyn/_nd_image.cpython-33m.so
kapteyn/profiles.cpython-33m.so
kapteyn/wcs.cpython-33m.so
kapteyn/rulers.py
kapteyn/interpolation.py
kapteyn/positions.py
kapteyn/maputils.py
kapteyn/kmpfit.cpython-33m.so
kapteyn/__init__.py
kapteyn/mplutil.py
kapteyn/shapes.py
kapteyn/filters.py
kapteyn/_ni_support.py
kapteyn/lut/idl5.lut
kapteyn/lut/random3.lut
kapteyn/lut/halley.lut
kapteyn/lut/rainbow3.lut
kapteyn/lut/color.lut
kapteyn/lut/random4.lut
kapteyn/lut/idl11.lut
kapteyn/lut/red.lut
kapteyn/lut/random1.lut
kapteyn/lut/staircase.lut
kapteyn/lut/pseudo2.lut
kapteyn/lut/light.lut
kapteyn/lut/heat.lut
kapteyn/lut/stairs9.lut
kapteyn/lut/alex.lut
kapteyn/lut/rainbow.lut
kapteyn/lut/manycol.lut
kapteyn/lut/rainbow4.lut
kapteyn/lut/rainbow5.lut
kapteyn/lut/idl12.lut
kapteyn/lut/pseudo1.lut
kapteyn/lut/pastel.lut
kapteyn/lut/idl14.lut
kapteyn/lut/ikon.lut
kapteyn/lut/standard.lut
kapteyn/lut/idl15.lut
kapteyn/lut/rainbow2.lut
kapteyn/lut/sunbow2.lut
kapteyn/lut/aips.lut
kapteyn/lut/lnspiral.lut
kapteyn/lut/blulut.lut
kapteyn/lut/idl4.lut
kapteyn/lut/real.lut
kapteyn/lut/blue.lut
kapteyn/lut/green.lut
kapteyn/lut/sunbow.lut
kapteyn/lut/backgr.lut
kapteyn/lut/kester.lut
kapteyn/lut/ramp.lut
kapteyn/lut/bw.lut
kapteyn/lut/random2.lut
kapteyn/lut/flag.lut
kapteyn/lut/random.lut
kapteyn/lut/ronekers.lut
kapteyn/lut/idl6.lut
kapteyn/lut/rainbow1.lut
kapteyn/lut/mousse.lut
kapteyn/lut/isophot.lut
kapteyn/lut/idl2.lut
kapteyn/lut/stairs8.lut
kapteyn/lut/smooth.lut
