Metadata-Version: 2.0
Name: kapteyn
Version: 2.3
Summary: Kapteyn Package: Python modules for astronomical applications
Home-page: http://www.astro.rug.nl/software/kapteyn/
Author: J.P. Terlouw, M.G.R. Vogelaar, M.A. Breddels
Author-email: gipsy@astro.rug.nl
License: BSD
Download-URL: http://www.astro.rug.nl/software/kapteyn/kapteyn-2.3.tar.gz
Platform: Linux
Platform: Mac OSX
Platform: Windows
Classifier: Development Status :: 5 - Production/Stable
Classifier: Programming Language :: Python
Classifier: Programming Language :: Cython
Classifier: Programming Language :: C
Classifier: Intended Audience :: Science/Research
Classifier: Topic :: Scientific/Engineering :: Astronomy
Classifier: Topic :: Scientific/Engineering :: Visualization
Classifier: Topic :: Scientific/Engineering :: Mathematics
Classifier: License :: OSI Approved :: BSD License
Classifier: License :: OSI Approved :: GNU Library or Lesser General Public License (LGPL)
Classifier: Operating System :: POSIX :: Linux
Classifier: Operating System :: MacOS :: MacOS X
Classifier: Operating System :: Microsoft :: Windows
